wordhord/__init__.py
wordhord/oetext.py
wordhord/ssp.py
wordhord/syllable.py
wordhord/utils.py
wordhord/wordhord.py
wordhord-0.0.3.dist-info/DESCRIPTION.rst
wordhord-0.0.3.dist-info/METADATA
wordhord-0.0.3.dist-info/RECORD
wordhord-0.0.3.dist-info/WHEEL
wordhord-0.0.3.dist-info/metadata.json
wordhord-0.0.3.dist-info/top_level.txt
