Metadata-Version: 2.0
Name: wordhord
Version: 0.0.3
Summary: GPLv3/Python3/toolbox for Old English text analyse
Home-page: https://github.com/suizokukan/wordhord
Author: Xavier Faure (suizokukan / 94.23.197.37)
Author-email: suizokukan@orange.fr
License: GPL-3.0
Keywords: language text
Platform: UNKNOWN
Classifier: Development Status :: 3 - Alpha
Classifier: Intended Audience :: Education
Classifier: Topic :: Utilities
Classifier: License :: OSI Approved :: GNU General Public License v3 (GPLv3)
Classifier: Programming Language :: Python :: 3
